{
    "Code": 0,
    "Message": "SUCCESS",
    "Data": [
        {
            "id": 36,
            "his_insect_id": 36,
            "cure_employee_id": 2,
            "cure_employee_name": "刘医生",
            "name": "第1次",
            "weight": "",
            "temperature": "",
            "discription": "体内驱虫第1次",
            "eventtime": "2023-05-13 09:47:03",
            "state": 1,
            "tag": 2,
            "hospital_name": "萌宠拾光动物医院",
            "hospital_id": 1,
            "is_chain": 0,
            "his_consumptions": [
                {
                    "add_employee_name": "付医生",
                    "id": 3433,
                    "order_value": 0,
                    "his_consumer_id": 2,
                    "his_consumer_name": "张秋芬",
                    "his_pet_id": 2,
                    "his_pet_name": "咪娅",
                    "his_bill_id": 1465,
                    "con_commodity_id": 1752,
                    "con_category_id": 60,
                    "con_category_name": "",
                    "top_category_id": 10,
                    "commodity_code": "P000001672",
                    "commodity_encode": "",
                    "commodity_name": "汉宠欣0.67ml",
                    "commodity_namepy": "HCX0.67ml",
                    "commodity_brand": "汉维宠仕",
                    "commodity_isuse_alias": 0,
                    "commodity_aliasname": "",
                    "commodity_standardname": "",
                    "commodity_standardcode": "",
                    "commodity_vender": "",
                    "commodity_format": "0.67ml",
                    "commodity_unit": "支",
                    "commodity_use_memberprice": 0,
                    "commodity_memberprice": 0,
                    "commodity_isuse_stock": 1,
                    "commodity_isuse_off": 0,
                    "commodity_isuse_batch": 0,
                    "commodity_isrecommend": 0,
                    "commodity_isexchange": 0,
                    "commodity_ismeal": 0,
                    "usages": "",
                    "usagesquantity": "",
                    "useunit": "",
                    "quantity": 1,
                    "price": 50,
                    "payprice": 50,
                    "bussinesstype": 11,
                    "sale_employee_id": 2,
                    "sale_employee_name": "刘医生",
                    "service_employee_id": 2,
                    "service_employee_name": "刘医生",
                    "cure_employee_id": 0,
                    "cure_employee_name": "",
                    "daily_id": 0,
                    "bill_type": 1,
                    "state": 0,
                    "mark": "",
                    "eventtime": "2023-05-13 09:48:14",
                    "meter_number": 0,
                    "his_consumption_id": 0,
                    "parent_id": 36,
                    "tag": 2,
                    "his_pet_code": "",
                    "is_count_stock": 0,
                    "sale_type": 0,
                    "sale_percent": 0,
                    "sale_royalty_price": 0,
                    "service_type": 0,
                    "service_percent": 0,
                    "service_royalty_price": 0,
                    "pay_state": 0,
                    "off": 0,
                    "lot_number": "",
                    "is_refund": 0,
                    "original_consumption_id": 0,
                    "is_commodity_deposit": 0,
                    "purchase_reminder": 0,
                    "only_update_usage": 0,
                    "usage_of_meal": null,
                    "select_model": 0,
                    "is_update_sm": 0,
                    "is_new_stock": 0,
                    "his_retreat_bill_id": 0
                }
            ]
        },
        {
            "id": 37,
            "his_insect_id": 36,
            "cure_employee_id": 2,
            "cure_employee_name": "刘医生",
            "name": "第2次",
            "weight": "",
            "temperature": "",
            "discription": "体内驱虫第2次",
            "eventtime": "2023-06-12 09:47:08",
            "state": 1,
            "tag": 2,
            "hospital_name": "萌宠拾光动物医院",
            "hospital_id": 1,
            "is_chain": 0,
            "his_consumptions": [
                {
                    "add_employee_name": "付医生",
                    "id": 3434,
                    "order_value": 0,
                    "his_consumer_id": 2,
                    "his_consumer_name": "张秋芬",
                    "his_pet_id": 2,
                    "his_pet_name": "咪娅",
                    "his_bill_id": 1465,
                    "con_commodity_id": 1727,
                    "con_category_id": 60,
                    "con_category_name": "",
                    "top_category_id": 10,
                    "commodity_code": "P000001647",
                    "commodity_encode": "",
                    "commodity_name": "海乐妙14mg",
                    "commodity_namepy": "HLM14mg",
                    "commodity_brand": "海正",
                    "commodity_isuse_alias": 0,
                    "commodity_aliasname": "",
                    "commodity_standardname": "",
                    "commodity_standardcode": "",
                    "commodity_vender": "",
                    "commodity_format": "14mg",
                    "commodity_unit": "片",
                    "commodity_use_memberprice": 0,
                    "commodity_memberprice": 0,
                    "commodity_isuse_stock": 1,
                    "commodity_isuse_off": 0,
                    "commodity_isuse_batch": 0,
                    "commodity_isrecommend": 0,
                    "commodity_isexchange": 0,
                    "commodity_ismeal": 0,
                    "usages": "",
                    "usagesquantity": "",
                    "useunit": "",
                    "quantity": 1,
                    "price": 40,
                    "payprice": 40,
                    "bussinesstype": 11,
                    "sale_employee_id": 2,
                    "sale_employee_name": "刘医生",
                    "service_employee_id": 2,
                    "service_employee_name": "刘医生",
                    "cure_employee_id": 0,
                    "cure_employee_name": "",
                    "daily_id": 0,
                    "bill_type": 1,
                    "state": 0,
                    "mark": "",
                    "eventtime": "2023-05-13 09:48:14",
                    "meter_number": 0,
                    "his_consumption_id": 0,
                    "parent_id": 37,
                    "tag": 2,
                    "his_pet_code": "",
                    "is_count_stock": 0,
                    "sale_type": 0,
                    "sale_percent": 0,
                    "sale_royalty_price": 0,
                    "service_type": 0,
                    "service_percent": 0,
                    "service_royalty_price": 0,
                    "pay_state": 0,
                    "off": 0,
                    "lot_number": "",
                    "is_refund": 0,
                    "original_consumption_id": 0,
                    "is_commodity_deposit": 0,
                    "purchase_reminder": 0,
                    "only_update_usage": 0,
                    "usage_of_meal": null,
                    "select_model": 0,
                    "is_update_sm": 0,
                    "is_new_stock": 0,
                    "his_retreat_bill_id": 0
                }
            ]
        }
    ]
}